afuzz/__init__.py
afuzz/settings.py
afuzz/db/backup.txt
afuzz/db/bad_strings.txt
afuzz/db/blacklist.txt
afuzz/db/dict.txt
afuzz/db/dict_bak.txt
afuzz/db/language.txt
afuzz/db/whitelist.txt
afuzz/lib/__init__.py
afuzz/lib/cmdline.py
afuzz/lib/config.py
afuzz/lib/dictionary.py
afuzz/lib/fuzzer.py
afuzz/lib/requester.py
afuzz/lib/response.py
afuzz/lib/result.py
afuzz/utils/__init__.py
afuzz/utils/common.py
afuzz/utils/headers.py
afuzz/utils/mimetype.py
Afuzz-0.1.11.dist-info/METADATA
Afuzz-0.1.11.dist-info/WHEEL
Afuzz-0.1.11.dist-info/entry_points.txt
Afuzz-0.1.11.dist-info/top_level.txt
Afuzz-0.1.11.dist-info/RECORD
