Metadata-Version: 2.1
Name: Afuzz
Version: 0.1.11
Summary: Afuzz
Home-page: https://github.com/rapiddns
Author: RapidDNS
Author-email: skyj96455@gmail.com
Keywords: afuzz,bug bounty,http,pentesting,security
Classifier: Development Status :: 5 - Production/Stable
Classifier: Environment :: Console
Classifier: License :: OSI Approved :: BSD License
Classifier: Programming Language :: Python :: 3
Classifier: Programming Language :: Python :: 3.8
Classifier: Programming Language :: Python :: 3.9
Classifier: Programming Language :: Python :: 3.10
Requires-Dist: httpx (==0.23.3)
Requires-Dist: httpx[http2]
Requires-Dist: asciistuff (==1.2.3)
Requires-Dist: prettytable (==3.6.0)
Requires-Dist: pandas (==1.5.3)
Requires-Dist: tldextract (==3.4.0)
Requires-Dist: defusedxml (==0.7.1)
Requires-Dist: IPy (==1.1)
